zohocrm/__init__.py
zohocrmapi-0.0.11.dist-info/LICENSE
zohocrmapi-0.0.11.dist-info/METADATA
zohocrmapi-0.0.11.dist-info/WHEEL
zohocrmapi-0.0.11.dist-info/top_level.txt
zohocrmapi-0.0.11.dist-info/RECORD
