Metadata-Version: 2.1
Name: zohocrmapi
Version: 0.0.11
Summary: A Zoho CRM API
Home-page: https://github.com/backupbrain/zoho-crm-api
Author: Adonis Gaitatzis
Author-email: backupbrain@gmail.com
License: UNKNOWN
Platform: UNKNOWN
Classifier: Programming Language :: Python :: 3
Classifier: License :: OSI Approved :: GNU General Public License v3 (GPLv3)
Classifier: Operating System :: OS Independent
Classifier: Development Status :: 4 - Beta
Classifier: Intended Audience :: Developers
Requires-Python: >=3.6
Requires-Dist: requests
